datalake_api/app.py
datalake_api/querier.py
datalake_api/__init__.py
datalake_api/v0.py
datalake_api/settings.py
datalake_api/static/index.html
datalake_api/static/swagger-ui.min.js
datalake_api/static/swagger-ui.js
datalake_api/static/o2c.html
datalake_api/static/lib/highlight.7.3.pack.js
datalake_api/static/lib/jquery.wiggle.min.js
datalake_api/static/lib/jquery.slideto.min.js
datalake_api/static/lib/jquery.ba-bbq.min.js
datalake_api/static/lib/handlebars-2.0.0.js
datalake_api/static/lib/jquery-1.8.0.min.js
datalake_api/static/lib/swagger-oauth.js
datalake_api/static/lib/underscore-min.js
datalake_api/static/lib/underscore-min.map
datalake_api/static/lib/backbone-min.js
datalake_api/static/lib/marked.js
datalake_api/static/fonts/droid-sans-v6-latin-regular.woff2
datalake_api/static/fonts/droid-sans-v6-latin-700.svg
datalake_api/static/fonts/droid-sans-v6-latin-700.ttf
datalake_api/static/fonts/droid-sans-v6-latin-regular.ttf
datalake_api/static/fonts/droid-sans-v6-latin-regular.eot
datalake_api/static/fonts/droid-sans-v6-latin-regular.woff
datalake_api/static/fonts/droid-sans-v6-latin-regular.svg
datalake_api/static/fonts/droid-sans-v6-latin-700.woff2
datalake_api/static/fonts/droid-sans-v6-latin-700.woff
datalake_api/static/fonts/droid-sans-v6-latin-700.eot
datalake_api/static/css/reset.css
datalake_api/static/css/screen.css
datalake_api/static/css/typography.css
datalake_api/static/css/print.css
datalake_api/static/css/style.css
datalake_api/static/lang/es.js
datalake_api/static/lang/pt.js
datalake_api/static/lang/translator.js
datalake_api/static/lang/en.js
datalake_api/static/lang/ru.js
datalake_api/static/images/explorer_icons.png
datalake_api/static/images/throbber.gif
datalake_api/static/images/favicon-32x32.png
datalake_api/static/images/favicon.ico
datalake_api/static/images/planet.png
datalake_api/static/images/favicon-16x16.png
datalake_api/static/images/logo_small.png
datalake_api-0.8.0.dist-info/RECORD
datalake_api-0.8.0.dist-info/METADATA
datalake_api-0.8.0.dist-info/DESCRIPTION.rst
datalake_api-0.8.0.dist-info/WHEEL
datalake_api-0.8.0.dist-info/top_level.txt
datalake_api-0.8.0.dist-info/metadata.json
