Metadata-Version: 2.0
Name: datalake-api
Version: 0.8.0
Summary: datalake_api ingests datalake metadata records
Home-page: https://github.com/planetlabs/datalake-api
Author: Brian Cavagnolo
Author-email: brian@planet.com
License: UNKNOWN
Platform: UNKNOWN
Requires-Dist: pyver (>=1.0.18)
Requires-Dist: memoized-property (>=1.0.2)
Requires-Dist: simplejson (>=3.3.1)
Requires-Dist: datalake-common (>=0.7)
Requires-Dist: Flask (>=0.10.1)
Requires-Dist: flask-swagger (==0.2.8)
Requires-Dist: boto3 (==1.1.3)
Requires-Dist: raven (>=5.6.0)
Provides-Extra: test
Requires-Dist: pytest (==2.7.2); extra == 'test'
